[
  {
    "symbol": "AUDD",
    "name": "Novatti Australian Digital Dollar",
    "decimals": 6,
    "version": "1",
    "eip3009Enabled": false,
    "issuer": "AUDC Pty Ltd (Novatti Group)",
    "networks": {
      "ethereum": {
        "chainId": 1,
        "address": "0x4cce605ed955295432958d8951d0b176c10720d5"
      },
      "base": {
        "chainId": 8453,
        "address": "0x449b3317a6d1efb1bc3ba0700c9eaa4ffff4ae65"
      }
    }
  },
  {
    "symbol": "AUDF",
    "name": "Forte AUD",
    "decimals": 6,
    "version": "1",
    "eip3009Enabled": false,
    "issuer": "Forte Securities Australia",
    "networks": {
      "ethereum": {
        "chainId": 1,
        "address": "0xd2a530170d71a9cfe1651fb468e2b98f7ed7456b"
      },
      "polygon": {
        "chainId": 137,
        "address": "0xd2a530170d71a9cfe1651fb468e2b98f7ed7456b"
      },
      "avalanche": {
        "chainId": 43114,
        "address": "0xd2a530170d71a9cfe1651fb468e2b98f7ed7456b"
      },
      "base": {
        "chainId": 8453,
        "address": "0xd2a530170d71a9cfe1651fb468e2b98f7ed7456b"
      }
    }
  },
  {
    "symbol": "AUDM",
    "name": "Macropod",
    "decimals": 6,
    "version": "1",
    "eip3009Enabled": false,
    "issuer": "Catena Digital Pty Ltd (MHC Digital Group & Catena Digital)",
    "networks": {
      "ethereum": {
        "chainId": 1,
        "address": "0x081599E4936D12c46Bd48913B2329115Cd26cbdd"
      }
    }
  },
  {
    "symbol": "NZDD",
    "name": "New Zealand Digital Dollar",
    "decimals": 18,
    "version": "1",
    "eip3009Enabled": false,
    "issuer": "ECDD Holdings Ltd (Easy Crypto)",
    "networks": {
      "ethereum": {
        "chainId": 1,
        "address": "0x2dd087589ce9c5b2d1b42e20d2519b3c8cf022b7"
      },
      "polygon": {
        "chainId": 137,
        "address": "0x2dd087589ce9c5b2d1b42e20d2519b3c8cf022b7"
      }
    }
  },
  {
    "symbol": "NZDS",
    "name": "NZD Stablecoin",
    "decimals": 6,
    "version": "1",
    "eip3009Enabled": false,
    "issuer": "Techemynt (FSP773214)",
    "networks": {
      "ethereum": {
        "chainId": 1,
        "address": "0xDa446fAd08277B4D2591536F204E018f32B6831c"
      }
    }
  }
]